Metadata-Version: 2.1
Name: veronica
Version: 0.2.8
Summary: UNKNOWN
Home-page: UNKNOWN
Author: Nirmal Khedkar
Author-email: nirmalhk7@gmail.com
License: MIT
Platform: UNKNOWN
Requires-Python: >=3.6
